keytotext/__init__.py
keytotext/dataset.py
keytotext/models.py
keytotext/pipeline.py
keytotext/trainer.py
keytotext-2.3.2.dist-info/LICENSE
keytotext-2.3.2.dist-info/WHEEL
keytotext-2.3.2.dist-info/METADATA
keytotext-2.3.2.dist-info/RECORD
