Metadata-Version: 1.1
Name: keytotext
Version: 2.3.2
Summary: Text Generation Using Keywords
Home-page: https://github.com/gagan3012/keytotext
Author: Gagan Bhatia
Author-email: gbhatia880@gmail.com
